Workbook

Sheet History of changes
E1: ESTIMATION | J1: No: BM-2-901-22
J2: Version: 1.5
J3: Issue Date: 10/03/2026
A4: SUN ASTERISK VIETNAM CO., LTD | J4: ISO/IEC 27001:2022 & ISO 9001:2015
A6: HISTORY OF CHANGES
A7: No | B7: Change Item | E7: Description of changes | J7: Change Date | L7: Version
A8: 1 | E8: Update format | J8: 44320
A9: 2 | B9: Sheet Note-Coeficient | E9: Change Working hours in a day from 8 hour to 7 hour | J9: 14/04/2023
A10: 3 | B10: Techical Suggestion | E10: Add new sheet about Technical Suggestion | J10: 28/06/2023
A11: 4 | B11: Sheet 00_Summary | E11: Update nội dung mục Assumptions | J11: 26/11/2024
A12: 5 | B12: Security Requirement | E12: Update thêm mục Security Requirement ở sheet 00_Summary Add new sheet about Security Requirement & Security Requirement (Recommendation) | J12: 45455
A13: 6 | B13: Sheet Summary | E13: Thay đổi Project Role theo thay đổi cơ cấu mới của tổ chức - PSM -> Project Leader | J13: 23/12/2024
A14: 7 | B14: Remove | E14: Remove 2 sheet: 04_Security Requirement và 04_Security Requirement (Recommendation) | J14: 45694
A15: 8 | B15: Add new | E15: Bổ sung sheet 04_Infrastructure for AWS dành cho hoạt động estimation liên quan đến AWS | J15: 21/11/2025
A16: 9 | B16: 00_Summary | E16: Bổ sung mục III. Documents List tại sheet 00_Summary | J16: 06/02/2026 | L16: v1.4
A17: 10 | B17: 00_Summary | E17: Tại sheet 00_Summary: - Đổi tên mục III. Documents List thành mục IV. Documents List - Thêm mới mục III. Deliveriable List: liệt kê danh sách các output cần bàn giao cho Khách hàng dựa trên sự thống nhất giữa Sun* và Khách hàng. | J17: 10/03/2026 | L17: v1.5
A18: 11 | B18: Add new | E18: Thêm mới sheet 05_Resource Plan: nhằm cung cấp cái nhìn tổng thể về kế hoạch phân bổ nguồn lực theo từng vai trò và theo từng giai đoạn/thời gian phát triển của dự án. | J18: 10/03/2026 | L18: v1.5

Sheet Technical Suggestion
B1: ESTIMATION | F1: No: BM-2-901-22
F2: Version: 1.5
F3: Issue Date: 10/03/2026
A4: SUN ASTERISK VIETNAM CO., LTD | F4: ISO/IEC 27001:2022 & ISO 9001:2015
A6: Reference document tại đây
A8: ■ Development strategy: | C8: MVP / POC
A9: ■ Type of service: | C9: Web
A10: ■ Programming language:
A11: ■ Framework:
A12: ■ Server or serverless: | C12: Server
A13: ■ Infrastructure diagram: | C13: Link to diagram
A14: ■ Infrastructure cost: | C14: Link to AWS/GCP... calculator
A15: ■ Use IaC (infrastructure as code) tool to build environment: | C15: Terraform
A16: ■ Web rendering method: | C16: Server Side Redering (SSR)
A17: ■ Use admin template tool: | C17: LaravelAdmin
A18: ■ Apply performance test: | C18: Yes
A19: ■ Suggest services for specific modules/functions:

Sheet 00_Summary
D1: ESTIMATION | K1: No: BM-2-901-22
K2: Version: 1.5
K3: Issue Date: 10/03/2026
A4: SUN ASTERISK VIETNAM CO., LTD | K4: ISO/IEC 27001:2022 & ISO 9001:2015
B6: I. Effort
B7: No. | C7: Role | D7: Total Effort (MM) | E7: Note
B8: 1 | C8: Backend
B9: 2 | C9: Frontend
B10: 3 | C10: Native App
B11: 4 | C11: QA
B12: 5 | C12: AI
B13: 6 | C13: Infrastructure
B14: 7 | C14: Design UI/UX
B15: 8 | C15: Specification
C16: Total
B19: II. Scope & Assumptions
B21: 1. In Scope
B22: The scope for estimate does include the following items:
B23: # | C23: Item | D23: Description | E23: Note
B24: 1
B25: 2
B27: 2. Out of Scope
B28: The estimation does not include the following items:
B29: # | C29: Item | D29: Description | E29: Note
B30: 1
B31: 2
B33: 3. Assumptions
B34: 3-1. Overall Assumptions | K34: → Japanese Translation 日本語訳（自動翻訳）
B35: # | C35: Item | E35: Applicable degree | F35: Assumptions | H35: Reason for not applicable | K35: # | L35: =IFERROR(__xludf.DUMMYFUNCTION("GOOGLETRANSLATE(C35,""en"",""ja"")"),"アイテム") -> アイテム | N35: =IFERROR(__xludf.DUMMYFUNCTION("GOOGLETRANSLATE(E35,""en"",""ja"")"),"該当する学位") -> 該当する学位 | O35: =IFERROR(__xludf.DUMMYFUNCTION("GOOGLETRANSLATE(F35,""en"",""ja"")"),"前提条件") -> 前提条件 | Q35: =IFERROR(__xludf.DUMMYFUNCTION("GOOGLETRANSLATE(H35,""en"",""ja"")"),"該当しない理由") -> 該当しない理由
B36: 1 | C36: Accuracy of this estimation | E36: Super Rough | K36: 1 | L36: 見積もりの精度 | N36: Super Rough
B37: 2 | C37: Roles and expected outputs of each role (What tasks will each role be responsible for, and what will they output?) Ref: Responsibility of each role: [JP] Onboarding for JPPM | D37: PSM | E37: TRUE | K37: 2 | L37: 各役割の役割と期待される成果 （各役割はどのようなタスクを担当し、どのような成果を出すのか？） 参考：各役割の責任：[JP] Onboarding for JPPM | M37: PSM | N37: TRUE
D38: BrSE | E38: TRUE | M38: BrSE | N38: TRUE
D39: Communicator | E39: TRUE | M39: Communicator | N39: TRUE
B40: 3 | C40: Roles and expected output from JP members (What are you expecting to get from JP side?) | E40: TRUE | K40: 3 | L40: JPメンバーの役割と期待される成果 （JP側から何を期待していますか？） | N40: TRUE
B41: 4 | C41: Schedule and expected inputs and outputs at each milestone (When and what will be output during the project period? When are dependent inputs expected to be completed/received?) Example: timeline for receiving existing database structure from customer and timeline for starting development | E41: Must have | K41: 4 | L41: 各マイルストーンにおけるスケジュールと予想される入出力 (プロジェクト期間中にいつ、どのような出力が行われるか？依存する入出力はいつ完了／受領される予定か？) 例: 顧客から既存のデータベース構造を受け取るまでのタイムラインと開発開始までのタイムライン | N41: Must have
B42: 5 | C42: Number of screens | E42: Must have | K42: 5 | L42: スクリーン数 | N42: Must have
B43: 6 | C43: Number of APIs per screen | E43: TRUE | K43: 6 | L43: 画面あたりのAPI数 | N43: TRUE
B44: 7 | C44: Interfaces | E44: TRUE | K44: 7 | L44: インターフェース | N44: TRUE
B45: 8 | C45: Forms ("Cho-hyo" in Japanese) | E45: TRUE | K45: 8 | L45: 帳簿（ちょうひょう） | N45: TRUE
B46: 9 | C46: System scale (How do you envision the number of users and infrastructure configuration? *If specified by the customer, attach a link to the customer request.) | E46: TRUE | K46: 9 | L46: システム規模 （ユーザー数とインフラ構成はどのように想定されていますか？ *お客様からご指定がある場合は、お客様リクエストへのリンクを添付してください。） | N46: TRUE
B47: 10 | C47: Non-functional requirements (What do you envision for SLA and security requirements? *If specified by the customer, attach a link to the customer request.) | E47: FALSE | K47: 10 | L47: 非機能要件 (SLAとセキュリティ要件についてはどのようなことを想定していますか？ *お客様からご指定がある場合は、お客様からのリクエストへのリンクを添付してください。) | N47: FALSE
B48: 11 | C48: Buffer rate (%) and its breakdown (Buffer for risk, such as change request, bugs and issue solving, technical difficulty only) | E48: Must have | K48: 11 | L48: バッファ率（%）とその内訳 （変更要求、バグや問題解決、技術的困難などのリスクに対するバッファのみ） | N48: Must have
B50: 3-2. Detail Assumptions per each role | K50: → Japanese Translation 日本語訳（自動翻訳）
B51: Role | C51: Item | E51: Applicable degree | F51: Assumptions | H51: Reason for not applicable | K51: =IFERROR(__xludf.DUMMYFUNCTION("GOOGLETRANSLATE(B51,""en"",""ja"")"),"役割") -> 役割 | L51: =IFERROR(__xludf.DUMMYFUNCTION("GOOGLETRANSLATE(C51,""en"",""ja"")"),"アイテム") -> アイテム | N51: =IFERROR(__xludf.DUMMYFUNCTION("GOOGLETRANSLATE(E51,""en"",""ja"")"),"該当する学位") -> 該当する学位 | O51: =IFERROR(__xludf.DUMMYFUNCTION("GOOGLETRANSLATE(F51,""en"",""ja"")"),"前提条件") -> 前提条件 | Q51: =IFERROR(__xludf.DUMMYFUNCTION("GOOGLETRANSLATE(H51,""en"",""ja"")"),"該当しない理由") -> 該当しない理由
B52: Backend | C52: Develop new system or Develop in existing System? | E52: Must have | K52: Backend | L52: =IFERROR(__xludf.DUMMYFUNCTION("GOOGLETRANSLATE(C52,""en"",""ja"")"),"新規システムを開発するか、既存システム内で開発するか？") -> 新規システムを開発するか、既存システム内で開発するか？ | N52: Must have
C53: Architecture (microservices, monolithic, multitenant) | E53: TRUE | L53: =IFERROR(__xludf.DUMMYFUNCTION("GOOGLETRANSLATE(C53,""en"",""ja"")"),"アーキテクチャ（マイクロサービス、モノリシック、マルチテナント）") -> アーキテクチャ（マイクロサービス、モノリシック、マルチテナント） | N53: TRUE | O53: =IFERROR(__xludf.DUMMYFUNCTION("iferror(GOOGLETRANSLATE(F53,""en"",""ja""),"""")"),"")
C54: Scope of work | D54: Unit Test | E54: TRUE | L54: =IFERROR(__xludf.DUMMYFUNCTION("GOOGLETRANSLATE(C54,""en"",""ja"")"),"作業範囲") -> 作業範囲 | M54: =IFERROR(__xludf.DUMMYFUNCTION("GOOGLETRANSLATE(D54,""en"",""ja"")"),"単体テスト") -> 単体テスト | N54: TRUE | O54: =IFERROR(__xludf.DUMMYFUNCTION("iferror(GOOGLETRANSLATE(F54,""en"",""ja""),"""")"),"")
D55: Provide system Design | E55: TRUE | M55: =IFERROR(__xludf.DUMMYFUNCTION("GOOGLETRANSLATE(D55,""en"",""ja"")"),"システム設計を提供する") -> システム設計を提供する | N55: TRUE | O55: =IFERROR(__xludf.DUMMYFUNCTION("iferror(GOOGLETRANSLATE(F55,""en"",""ja""),"""")"),"")
D56: Provide API Design | E56: TRUE | M56: =IFERROR(__xludf.DUMMYFUNCTION("GOOGLETRANSLATE(D56,""en"",""ja"")"),"API設計を提供する") -> API設計を提供する | N56: TRUE | O56: =IFERROR(__xludf.DUMMYFUNCTION("iferror(GOOGLETRANSLATE(F56,""en"",""ja""),"""")"),"")
D57: Provide DB Design | E57: TRUE | M57: =IFERROR(__xludf.DUMMYFUNCTION("GOOGLETRANSLATE(D57,""en"",""ja"")"),"データベース設計を提供する") -> データベース設計を提供する | N57: TRUE | O57: =IFERROR(__xludf.DUMMYFUNCTION("iferror(GOOGLETRANSLATE(F57,""en"",""ja""),"""")"),"")
D58: Integrate CI/CD | E58: TRUE | M58: =IFERROR(__xludf.DUMMYFUNCTION("GOOGLETRANSLATE(D58,""en"",""ja"")"),"CI/CDを統合する") -> CI/CDを統合する | N58: TRUE | O58: =IFERROR(__xludf.DUMMYFUNCTION("iferror(GOOGLETRANSLATE(F58,""en"",""ja""),"""")"),"")
D59: Intergrate third parties services | E59: TRUE | M59: =IFERROR(__xludf.DUMMYFUNCTION("GOOGLETRANSLATE(D59,""en"",""ja"")"),"サードパーティサービスを統合する") -> サードパーティサービスを統合する | N59: TRUE | O59: =IFERROR(__xludf.DUMMYFUNCTION("iferror(GOOGLETRANSLATE(F59,""en"",""ja""),"""")"),"")
D60: Develop payment related functions | E60: TRUE | M60: =IFERROR(__xludf.DUMMYFUNCTION("GOOGLETRANSLATE(D60,""en"",""ja"")"),"支払い関連機能の開発") -> 支払い関連機能の開発 | N60: TRUE | O60: =IFERROR(__xludf.DUMMYFUNCTION("iferror(GOOGLETRANSLATE(F60,""en"",""ja""),"""")"),"")
D61: Migrate data from old system | E61: TRUE | M61: =IFERROR(__xludf.DUMMYFUNCTION("GOOGLETRANSLATE(D61,""en"",""ja"")"),"古いシステムからデータを移行する") -> 古いシステムからデータを移行する | N61: TRUE | O61: =IFERROR(__xludf.DUMMYFUNCTION("iferror(GOOGLETRANSLATE(F61,""en"",""ja""),"""")"),"")
D62: Production Deployment | E62: TRUE | M62: =IFERROR(__xludf.DUMMYFUNCTION("GOOGLETRANSLATE(D62,""en"",""ja"")"),"本番環境への展開") -> 本番環境への展開 | N62: TRUE | O62: =IFERROR(__xludf.DUMMYFUNCTION("iferror(GOOGLETRANSLATE(F62,""en"",""ja""),"""")"),"")
C63: Other assumed risks and assumptions | E63: Must have | L63: =IFERROR(__xludf.DUMMYFUNCTION("GOOGLETRANSLATE(C63,""en"",""ja"")"),"その他の想定リスクおよび前提条件") -> その他の想定リスクおよび前提条件 | N63: Must have | O63: =IFERROR(__xludf.DUMMYFUNCTION("iferror(GOOGLETRANSLATE(F63,""en"",""ja""),"""")"),"")
C64: Buffer rate (%) | E64: Must have | L64: =IFERROR(__xludf.DUMMYFUNCTION("GOOGLETRANSLATE(C64,""en"",""ja"")"),"バッファ率（％）") -> バッファ率（％） | N64: Must have | O64: =IFERROR(__xludf.DUMMYFUNCTION("iferror(GOOGLETRANSLATE(F64,""en"",""ja""),"""")"),"")
B65: Frontend | C65: Develop new system or Develop in existing System? | E65: Must have | K65: Frontend | L65: =IFERROR(__xludf.DUMMYFUNCTION("GOOGLETRANSLATE(C65,""en"",""ja"")"),"新規システムを開発するか、既存システム内で開発するか？") -> 新規システムを開発するか、既存システム内で開発するか？ | N65: Must have | O65: =IFERROR(__xludf.DUMMYFUNCTION("iferror(GOOGLETRANSLATE(F65,""en"",""ja""),"""")"),"")
C66: Architectural assumptions - Frameworks and libraries used - Whether SSR or CSR is applied | E66: TRUE | L66: =IFERROR(__xludf.DUMMYFUNCTION("GOOGLETRANSLATE(C66,""en"",""ja"")"),"アーキテクチャ上の前提条件 - 使用するフレームワークとライブラリ - SSRまたはCSRの適用の有無") -> アーキテクチャ上の前提条件 - 使用するフレームワークとライブラリ - SSRまたはCSRの適用の有無 | N66: TRUE | O66: =IFERROR(__xludf.DUMMYFUNCTION("iferror(GOOGLETRANSLATE(F66,""en"",""ja""),"""")"),"")
C67: Browser and versions (Chrome, Safari, IE etc) | E67: TRUE | L67: =IFERROR(__xludf.DUMMYFUNCTION("GOOGLETRANSLATE(C67,""en"",""ja"")"),"ブラウザとバージョン（Chrome、Safari、IEなど）") -> ブラウザとバージョン（Chrome、Safari、IEなど） | N67: TRUE | O67: =IFERROR(__xludf.DUMMYFUNCTION("iferror(GOOGLETRANSLATE(F67,""en"",""ja""),"""")"),"")
C68: Scope of work | D68: Responsive design | E68: TRUE | L68: =IFERROR(__xludf.DUMMYFUNCTION("GOOGLETRANSLATE(C68,""en"",""ja"")"),"作業範囲") -> 作業範囲 | M68: =IFERROR(__xludf.DUMMYFUNCTION("GOOGLETRANSLATE(D68,""en"",""ja"")"),"レスポンシブデザイン") -> レスポンシブデザイン | N68: TRUE | O68: =IFERROR(__xludf.DUMMYFUNCTION("iferror(GOOGLETRANSLATE(F68,""en"",""ja""),"""")"),"")
D69: State management | E69: TRUE | M69: =IFERROR(__xludf.DUMMYFUNCTION("GOOGLETRANSLATE(D69,""en"",""ja"")"),"国家管理") -> 国家管理 | N69: TRUE | O69: =IFERROR(__xludf.DUMMYFUNCTION("iferror(GOOGLETRANSLATE(F69,""en"",""ja""),"""")"),"")
D70: Automated testing | E70: TRUE | M70: =IFERROR(__xludf.DUMMYFUNCTION("GOOGLETRANSLATE(D70,""en"",""ja"")"),"自動テスト") -> 自動テスト | N70: TRUE | O70: =IFERROR(__xludf.DUMMYFUNCTION("iferror(GOOGLETRANSLATE(F70,""en"",""ja""),"""")"),"")
D71: Unit test | E71: TRUE | M71: =IFERROR(__xludf.DUMMYFUNCTION("GOOGLETRANSLATE(D71,""en"",""ja"")"),"単体テスト") -> 単体テスト | N71: TRUE | O71: =IFERROR(__xludf.DUMMYFUNCTION("iferror(GOOGLETRANSLATE(F71,""en"",""ja""),"""")"),"")
D72: SEO(Google Analytics, OGP tag, SSR) | E72: TRUE | M72: =IFERROR(__xludf.DUMMYFUNCTION("GOOGLETRANSLATE(D72,""en"",""ja"")"),"SEO（Google Analytics、OGPタグ、SSR）") -> SEO（Google Analytics、OGPタグ、SSR） | N72: TRUE | O72: =IFERROR(__xludf.DUMMYFUNCTION("iferror(GOOGLETRANSLATE(F72,""en"",""ja""),"""")"),"")
D73: Intergrate third parties services | E73: TRUE | M73: =IFERROR(__xludf.DUMMYFUNCTION("GOOGLETRANSLATE(D73,""en"",""ja"")"),"サードパーティサービスを統合する") -> サードパーティサービスを統合する | N73: TRUE | O73: =IFERROR(__xludf.DUMMYFUNCTION("iferror(GOOGLETRANSLATE(F73,""en"",""ja""),"""")"),"")
D74: Integrate CI/CD | E74: TRUE | M74: =IFERROR(__xludf.DUMMYFUNCTION("GOOGLETRANSLATE(D74,""en"",""ja"")"),"CI/CDを統合する") -> CI/CDを統合する | N74: TRUE | O74: =IFERROR(__xludf.DUMMYFUNCTION("iferror(GOOGLETRANSLATE(F74,""en"",""ja""),"""")"),"")
D75: Production Deployment | E75: TRUE | M75: =IFERROR(__xludf.DUMMYFUNCTION("GOOGLETRANSLATE(D75,""en"",""ja"")"),"本番環境への展開") -> 本番環境への展開 | N75: TRUE | O75: =IFERROR(__xludf.DUMMYFUNCTION("iferror(GOOGLETRANSLATE(F75,""en"",""ja""),"""")"),"")
C76: Other assumed risks and assumptions | E76: Must have | L76: =IFERROR(__xludf.DUMMYFUNCTION("GOOGLETRANSLATE(C76,""en"",""ja"")"),"その他の想定リスクおよび前提条件") -> その他の想定リスクおよび前提条件 | N76: Must have | O76: =IFERROR(__xludf.DUMMYFUNCTION("iferror(GOOGLETRANSLATE(F76,""en"",""ja""),"""")"),"")
C77: Buffer rate (%) | E77: Must have | L77: =IFERROR(__xludf.DUMMYFUNCTION("GOOGLETRANSLATE(C77,""en"",""ja"")"),"バッファ率（％）") -> バッファ率（％） | N77: Must have | O77: =IFERROR(__xludf.DUMMYFUNCTION("iferror(GOOGLETRANSLATE(F77,""en"",""ja""),"""")"),"")
B78: Mobile | C78: Develop new system or Develop in existing System? | E78: Must have | K78: Mobile | L78: =IFERROR(__xludf.DUMMYFUNCTION("GOOGLETRANSLATE(C78,""en"",""ja"")"),"新規システムを開発するか、既存システム内で開発するか？") -> 新規システムを開発するか、既存システム内で開発するか？ | N78: Must have | O78: =IFERROR(__xludf.DUMMYFUNCTION("iferror(GOOGLETRANSLATE(F78,""en"",""ja""),"""")"),"")
C79: OS and versions (iOS, Android) | E79: TRUE | L79: =IFERROR(__xludf.DUMMYFUNCTION("GOOGLETRANSLATE(C79,""en"",""ja"")"),"OSとバージョン（iOS、Android）") -> OSとバージョン（iOS、Android） | N79: TRUE | O79: =IFERROR(__xludf.DUMMYFUNCTION("iferror(GOOGLETRANSLATE(F79,""en"",""ja""),"""")"),"")
C80: Scope of work | D80: Unit test | E80: TRUE | L80: =IFERROR(__xludf.DUMMYFUNCTION("GOOGLETRANSLATE(C80,""en"",""ja"")"),"作業範囲") -> 作業範囲 | M80: =IFERROR(__xludf.DUMMYFUNCTION("GOOGLETRANSLATE(D80,""en"",""ja"")"),"単体テスト") -> 単体テスト | N80: TRUE | O80: =IFERROR(__xludf.DUMMYFUNCTION("iferror(GOOGLETRANSLATE(F80,""en"",""ja""),"""")"),"")
D81: Intergrate third parties services | E81: TRUE | M81: =IFERROR(__xludf.DUMMYFUNCTION("GOOGLETRANSLATE(D81,""en"",""ja"")"),"サードパーティサービスを統合する") -> サードパーティサービスを統合する | N81: TRUE | O81: =IFERROR(__xludf.DUMMYFUNCTION("iferror(GOOGLETRANSLATE(F81,""en"",""ja""),"""")"),"")
D82: Integrate CI/CD | E82: TRUE | M82: =IFERROR(__xludf.DUMMYFUNCTION("GOOGLETRANSLATE(D82,""en"",""ja"")"),"CI/CDを統合する") -> CI/CDを統合する | N82: TRUE | O82: =IFERROR(__xludf.DUMMYFUNCTION("iferror(GOOGLETRANSLATE(F82,""en"",""ja""),"""")"),"")
D83: Play store / App store publish | E83: TRUE | M83: =IFERROR(__xludf.DUMMYFUNCTION("GOOGLETRANSLATE(D83,""en"",""ja"")"),"Playストア/Appストアで公開") -> Playストア/Appストアで公開 | N83: TRUE | O83: =IFERROR(__xludf.DUMMYFUNCTION("iferror(GOOGLETRANSLATE(F83,""en"",""ja""),"""")"),"")
C84: Other assumed risks and assumptions | E84: Must have | L84: =IFERROR(__xludf.DUMMYFUNCTION("GOOGLETRANSLATE(C84,""en"",""ja"")"),"その他の想定リスクおよび前提条件") -> その他の想定リスクおよび前提条件 | N84: Must have | O84: =IFERROR(__xludf.DUMMYFUNCTION("iferror(GOOGLETRANSLATE(F84,""en"",""ja""),"""")"),"")
C85: Buffer rate (%) | E85: Must have | L85: =IFERROR(__xludf.DUMMYFUNCTION("GOOGLETRANSLATE(C85,""en"",""ja"")"),"バッファ率（％）") -> バッファ率（％） | N85: Must have | O85: =IFERROR(__xludf.DUMMYFUNCTION("iferror(GOOGLETRANSLATE(F85,""en"",""ja""),"""")"),"")
B86: QA | C86: Productivity | D86: Test case creation | E86: Must have | F86: [ ] case/1 man-day | K86: QA | L86: =IFERROR(__xludf.DUMMYFUNCTION("GOOGLETRANSLATE(C86,""en"",""ja"")"),"生産性") -> 生産性 | M86: =IFERROR(__xludf.DUMMYFUNCTION("GOOGLETRANSLATE(D86,""en"",""ja"")"),"テストケースの作成") -> テストケースの作成 | N86: Must have | O86: =IFERROR(__xludf.DUMMYFUNCTION("iferror(GOOGLETRANSLATE(F86,""en"",""ja""),"""")"),"[ ] 症例/1人日") -> [ ] 症例/1人日
D87: Test execution and bug identification | E87: Must have | F87: [ ] case/1 man-day | M87: =IFERROR(__xludf.DUMMYFUNCTION("GOOGLETRANSLATE(D87,""en"",""ja"")"),"テスト実行とバグの特定") -> テスト実行とバグの特定 | N87: Must have | O87: =IFERROR(__xludf.DUMMYFUNCTION("iferror(GOOGLETRANSLATE(F87,""en"",""ja""),"""")"),"[ ] 症例/1人日") -> [ ] 症例/1人日
D88: Final inspection effort in total man-hours | E88: Must have | F88: [ ] % | M88: =IFERROR(__xludf.DUMMYFUNCTION("GOOGLETRANSLATE(D88,""en"",""ja"")"),"最終検査にかかる総工数") -> 最終検査にかかる総工数 | N88: Must have | O88: =IFERROR(__xludf.DUMMYFUNCTION("iferror(GOOGLETRANSLATE(F88,""en"",""ja""),"""")"),"[ ] %") -> [ ] %
D89: Expected bug occurrence rate | E89: Must have | F89: [ ] % | M89: =IFERROR(__xludf.DUMMYFUNCTION("GOOGLETRANSLATE(D89,""en"",""ja"")"),"予想されるバグ発生率") -> 予想されるバグ発生率 | N89: Must have | O89: =IFERROR(__xludf.DUMMYFUNCTION("iferror(GOOGLETRANSLATE(F89,""en"",""ja""),"""")"),"[ ] %") -> [ ] %
C90: Testing scope | D90: Function test | E90: TRUE | L90: =IFERROR(__xludf.DUMMYFUNCTION("GOOGLETRANSLATE(C90,""en"",""ja"")"),"テスト範囲") -> テスト範囲 | M90: =IFERROR(__xludf.DUMMYFUNCTION("GOOGLETRANSLATE(D90,""en"",""ja"")"),"機能テスト") -> 機能テスト | N90: TRUE | O90: =IFERROR(__xludf.DUMMYFUNCTION("iferror(GOOGLETRANSLATE(F90,""en"",""ja""),"""")"),"")
D91: Integration test | E91: TRUE | M91: =IFERROR(__xludf.DUMMYFUNCTION("GOOGLETRANSLATE(D91,""en"",""ja"")"),"統合テスト") -> 統合テスト | N91: TRUE | O91: =IFERROR(__xludf.DUMMYFUNCTION("iferror(GOOGLETRANSLATE(F91,""en"",""ja""),"""")"),"")
D92: E2E test (Screen, API end point) | E92: TRUE | M92: =IFERROR(__xludf.DUMMYFUNCTION("GOOGLETRANSLATE(D92,""en"",""ja"")"),"エンドツーエンドテスト（画面、APIエンドポイント）") -> エンドツーエンドテスト（画面、APIエンドポイント） | N92: TRUE | O92: =IFERROR(__xludf.DUMMYFUNCTION("iferror(GOOGLETRANSLATE(F92,""en"",""ja""),"""")"),"")
D93: Regression test | E93: TRUE | M93: リグレッションテスト | N93: TRUE | O93: =IFERROR(__xludf.DUMMYFUNCTION("iferror(GOOGLETRANSLATE(F93,""en"",""ja""),"""")"),"")
D94: Other test | E94: TRUE | M94: =IFERROR(__xludf.DUMMYFUNCTION("GOOGLETRANSLATE(D94,""en"",""ja"")"),"その他のテスト") -> その他のテスト | N94: TRUE | O94: =IFERROR(__xludf.DUMMYFUNCTION("iferror(GOOGLETRANSLATE(F94,""en"",""ja""),"""")"),"")
D95: Environments to be tested and range of test cases covered for each environment | E95: Must have | M95: =IFERROR(__xludf.DUMMYFUNCTION("GOOGLETRANSLATE(D95,""en"",""ja"")"),"テスト対象環境と、各環境でカバーされるテストケースの範囲") -> テスト対象環境と、各環境でカバーされるテストケースの範囲 | N95: Must have | O95: =IFERROR(__xludf.DUMMYFUNCTION("iferror(GOOGLETRANSLATE(F95,""en"",""ja""),"""")"),"")
C96: Buffer rate (%) | E96: Must have | L96: =IFERROR(__xludf.DUMMYFUNCTION("GOOGLETRANSLATE(C96,""en"",""ja"")"),"バッファ率（％）") -> バッファ率（％） | N96: Must have
B97: AI | C97: Data flow in the AI scope | E97: TRUE | K97: AI | L97: AI スコープ内のデータ フロー | N97: TRUE
C98: Architecture in the AI ​​scope | E98: TRUE | L98: AIの範囲におけるアーキテクチャ | N98: TRUE
C99: AI models and AI services | E99: TRUE | L99: AIモデルとAIサービス | N99: TRUE
C100: Estimated cost of AI infrastructure (at the time of development and operation after release) | E100: TRUE | L100: AIインフラの概算費用（開発時、リリース後の運用時） | N100: TRUE
C101: Possibility of training (tuning) of AI models | E101: TRUE | L101: AIモデルのトレーニング（チューニング）が可能 | N101: TRUE
C102: Number of data required when training (tuning) an AI model | E102: TRUE | L102: AIモデルのトレーニング（チューニング）時に必要なデータ数 | N102: TRUE
C103: Prerequisites for implementing AI models and degree of difficulty in realizing them | E103: TRUE | L103: AIモデル導入の前提条件と実現難易度 | N103: TRUE
C104: Other assumed risks and assumptions (if not available, write “none”) | E104: Must have | L104: その他の想定されるリスクと仮定 (利用できない場合は「なし」と記入してください) | N104: Must have
C105: Buffer value (%) | E105: Must have | L105: =IFERROR(__xludf.DUMMYFUNCTION("GOOGLETRANSLATE(C105,""en"",""ja"")"),"バッファ値（％）") -> バッファ値（％） | N105: Must have
B106: Infrastructure | C106: Building environment; Dev, Stag, UAT, Prod etc | E106: Must have | K106: Infrastructure | L106: =IFERROR(__xludf.DUMMYFUNCTION("GOOGLETRANSLATE(C106,""en"",""ja"")"),"構築環境；開発、ステージング、UAT、本番など") -> 構築環境；開発、ステージング、UAT、本番など | N106: Must have | O106: =IFERROR(__xludf.DUMMYFUNCTION("iferror(GOOGLETRANSLATE(F106,""en"",""ja""),"""")"),"")
C107: Cloud service selection and architecture | E107: TRUE | L107: =IFERROR(__xludf.DUMMYFUNCTION("GOOGLETRANSLATE(C107,""en"",""ja"")"),"クラウドサービスの選択とアーキテクチャ") -> クラウドサービスの選択とアーキテクチャ | N107: TRUE | O107: =IFERROR(__xludf.DUMMYFUNCTION("iferror(GOOGLETRANSLATE(F107,""en"",""ja""),"""")"),"")
...

Sheet 01_Server
E1: ESTIMATION | K1: No: BM-2-901-22
K2: Version: 1.5
K3: Issue Date: 10/03/2026
B4: SUN ASTERISK VIETNAM CO., LTD | K4: ISO/IEC 27001:2022 & ISO 9001:2015
B6: Server
B8: Total (MM) | F8: =SUM(F13:F205)*(1+Appendix!$B$8)/Appendix!$B$13 -> 8.06 | G8: =SUM(G13:G205)*(1+Appendix!$B$8)/Appendix!$B$13 -> 2.418 | H8: =SUM(H13:H205)*(1+Appendix!$B$8)/Appendix!$B$13 -> 5.642 | I8: =SUM(I13:I205)*(1+Appendix!$B$8)/Appendix!$B$13 -> 0.585 | J8: =SUM(J13:J205)*(1+Appendix!$B$8)/Appendix!$B$13 -> 0.1755 | K8: =SUM(K13:K205)*(1+Appendix!$B$8)/Appendix!$B$13 -> 0.4095 | L8: =SUM(L13:L205)*(1+Appendix!$B$8)/Appendix!$B$13 -> 0.585
B10: No | C10: Category | D10: Screen・Feature | E10: Task | F10: Effort（Man-days） | M10: Note
F11: Backend | I11: Frontend | L11: DesignUX/UI
F12: Implement | G12: FixBug | H12: Unit Test | I12: Implement | J12: FixBug | K12: Unit Test
B13: 1 | C13: 共通 | D13: ログイン・ログアウト | F13: 2 | G13: =F13*Appendix!$B$11 -> 0.6 | H13: =F13*Appendix!$B$9 -> 1.4 | I13: 1 | J13: =I13*Appendix!$B$11 -> 0.3 | K13: =I13*Appendix!$B$9 -> 0.7 | L13: 1
B14: 2 | D14: WF再発行 メール送信 | F14: 1.5 | G14: =F14*Appendix!$B$11 -> 0.45 | H14: =F14*Appendix!$B$9 -> 1.05 | I14: 1 | J14: =I14*Appendix!$B$11 -> 0.3 | K14: =I14*Appendix!$B$9 -> 0.7 | L14: 1
B15: 3 | D15: WF再設定 | F15: 1.5 | G15: =F15*Appendix!$B$11 -> 0.45 | H15: =F15*Appendix!$B$9 -> 1.05 | I15: 1 | J15: =I15*Appendix!$B$11 -> 0.3 | K15: =I15*Appendix!$B$9 -> 0.7 | L15: 1
B16: 4 | C16: Contractor | D16: 契約者情報登録 | F16: 3 | G16: =F16*Appendix!$B$11 -> 0.9 | H16: =F16*Appendix!$B$9 -> 2.1 | I16: 1 | J16: =I16*Appendix!$B$11 -> 0.3 | K16: =I16*Appendix!$B$9 -> 0.7 | L16: 1
B17: 5 | D17: 契約情報登録 | F17: 3 | G17: =F17*Appendix!$B$11 -> 0.9 | H17: =F17*Appendix!$B$9 -> 2.1 | I17: 1 | J17: =I17*Appendix!$B$11 -> 0.3 | K17: =I17*Appendix!$B$9 -> 0.7 | L17: 1
B18: 6 | D18: 決済情報登録 | F18: 3 | G18: =F18*Appendix!$B$11 -> 0.9 | H18: =F18*Appendix!$B$9 -> 2.1 | I18: 0 | J18: =I18*Appendix!$B$11 -> 0 | K18: =I18*Appendix!$B$9 -> 0 | L18: 0
B19: 7 | D19: トップ | F19: 2 | G19: =F19*Appendix!$B$11 -> 0.6 | H19: =F19*Appendix!$B$9 -> 1.4 | I19: 0 | J19: =I19*Appendix!$B$11 -> 0 | K19: =I19*Appendix!$B$9 -> 0 | L19: 0
B20: 8 | D20: Manager一覧 | F20: 3 | G20: =F20*Appendix!$B$11 -> 0.9 | H20: =F20*Appendix!$B$9 -> 2.1 | I20: 0 | J20: =I20*Appendix!$B$11 -> 0 | K20: =I20*Appendix!$B$9 -> 0 | L20: 0
B21: 9 | D21: Manager登録・編集・削除 | F21: 3 | G21: =F21*Appendix!$B$11 -> 0.9 | H21: =F21*Appendix!$B$9 -> 2.1 | I21: 0 | J21: =I21*Appendix!$B$11 -> 0 | K21: =I21*Appendix!$B$9 -> 0 | L21: 0
B22: 10 | C22: Manager | D22: アカウント登録 | F22: 3 | G22: =F22*Appendix!$B$11 -> 0.9 | H22: =F22*Appendix!$B$9 -> 2.1 | I22: 0 | J22: =I22*Appendix!$B$11 -> 0 | K22: =I22*Appendix!$B$9 -> 0 | L22: 0
B23: 11 | D23: Manager一覧 | F23: 2 | G23: =F23*Appendix!$B$11 -> 0.6 | H23: =F23*Appendix!$B$9 -> 1.4 | I23: 0 | J23: =I23*Appendix!$B$11 -> 0 | K23: =I23*Appendix!$B$9 -> 0 | L23: 0
B24: 12 | D24: Manager登録・編集・削除 | F24: 3 | G24: =F24*Appendix!$B$11 -> 0.9 | H24: =F24*Appendix!$B$9 -> 2.1 | I24: 0 | J24: =I24*Appendix!$B$11 -> 0 | K24: =I24*Appendix!$B$9 -> 0 | L24: 0
B25: 13 | D25: グループ一覧 | F25: 2 | G25: =F25*Appendix!$B$11 -> 0.6 | H25: =F25*Appendix!$B$9 -> 1.4 | I25: 0 | J25: =I25*Appendix!$B$11 -> 0 | K25: =I25*Appendix!$B$9 -> 0 | L25: 0
B26: 14 | D26: グループ登録・編集・削除 | F26: 3 | G26: =F26*Appendix!$B$11 -> 0.9 | H26: =F26*Appendix!$B$9 -> 2.1 | I26: 0 | J26: =I26*Appendix!$B$11 -> 0 | K26: =I26*Appendix!$B$9 -> 0 | L26: 0
B27: 15 | D27: Managerカレンダー | F27: 5 | G27: =F27*Appendix!$B$11 -> 1.5 | H27: =F27*Appendix!$B$9 -> 3.5 | I27: 0 | J27: =I27*Appendix!$B$11 -> 0 | K27: =I27*Appendix!$B$9 -> 0 | L27: 0
B28: 16 | D28: トレーニング登録・編集 | F28: 3 | G28: =F28*Appendix!$B$11 -> 0.9 | H28: =F28*Appendix!$B$9 -> 2.1 | I28: 0 | J28: =I28*Appendix!$B$11 -> 0 | K28: =I28*Appendix!$B$9 -> 0 | L28: 0
B29: 17 | D29: イベント登録・編集 | F29: 3 | G29: =F29*Appendix!$B$11 -> 0.9 | H29: =F29*Appendix!$B$9 -> 2.1 | I29: 0 | J29: =I29*Appendix!$B$11 -> 0 | K29: =I29*Appendix!$B$9 -> 0 | L29: 0
B30: 18 | D30: トレーニングアイテム一覧 | F30: 2 | G30: =F30*Appendix!$B$11 -> 0.6 | H30: =F30*Appendix!$B$9 -> 1.4 | I30: 0 | J30: =I30*Appendix!$B$11 -> 0 | K30: =I30*Appendix!$B$9 -> 0 | L30: 0
B31: 19 | D31: トレーニングアイテム登録・編集・削除 | F31: 2 | G31: =F31*Appendix!$B$11 -> 0.6 | H31: =F31*Appendix!$B$9 -> 1.4 | I31: 0 | J31: =I31*Appendix!$B$11 -> 0 | K31: =I31*Appendix!$B$9 -> 0 | L31: 0
B32: 20 | D32: Athlete一覧 | F32: 2 | G32: =F32*Appendix!$B$11 -> 0.6 | H32: =F32*Appendix!$B$9 -> 1.4 | I32: 0 | J32: =I32*Appendix!$B$11 -> 0 | K32: =I32*Appendix!$B$9 -> 0 | L32: 0
B33: 21 | D33: Athlete登録・削除 | F33: 3 | G33: =F33*Appendix!$B$11 -> 0.9 | H33: =F33*Appendix!$B$9 -> 2.1 | I33: 0 | J33: =I33*Appendix!$B$11 -> 0 | K33: =I33*Appendix!$B$9 -> 0 | L33: 0
B34: 22 | D34: 各種情報推移 | F34: 7 | G34: =F34*Appendix!$B$11 -> 2.1 | H34: =F34*Appendix!$B$9 -> 4.9 | I34: 0 | J34: =I34*Appendix!$B$11 -> 0 | K34: =I34*Appendix!$B$9 -> 0 | L34: 0
... B40: 34 | D40: 退会 | F40: 1 | G40: =F40*Appendix!$B$11 -> 0.3 | H40: =F40*Appendix!$B$9 -> 0.7 | I40: 0 | J40: =I40*Appendix!$B$11 -> 0 | K40: =I40*Appendix!$B$9 -> 0 | L40: 0
B41: 23 | C41: Admin | D41: 加盟コントラクター承認 | F41: 3 | G41: =F41*Appendix!$B$11 -> 0.9 | H41: =F41*Appendix!$B$9 -> 2.1 | I41: 1 | J41: =I41*Appendix!$B$11 -> 0.3 | K41: =I41*Appendix!$B$9 -> 0.7 | L41: 1
B42: 24 | D42: 競技団体告知登録 | F42: 2 | G42: =F42*Appendix!$B$11 -> 0.6 | H42: =F42*Appendix!$B$9 -> 1.4 | I42: 1 | J42: =I42*Appendix!$B$11 -> 0.3 | K42: =I42*Appendix!$B$9 -> 0.7 | L42: 1
B43: 25 | D43: 問い合わせ対応 | F43: 6.5 | G43: =F43*Appendix!$B$11 -> 1.95 | H43: =F43*Appendix!$B$9 -> 4.55 | I43: 1 | J43: =I43*Appendix!$B$11 -> 0.3 | K43: =I43*Appendix!$B$9 -> 0.7 | L43: 1
B44: 26 | D44: ユーザー情報管理 | F44: 4.5 | G44: =F44*Appendix!$B$11 -> 1.35 | H44: =F44*Appendix!$B$9 -> 3.15 | I44: 1 | J44: =I44*Appendix!$B$11 -> 0.3 | K44: =I44*Appendix!$B$9 -> 0.7 | L44: 1
B45: 27 | D45: 契約情報管理 | F45: 4.5 | G45: =F45*Appendix!$B$11 -> 1.35 | H45: =F45*Appendix!$B$9 -> 3.15 | I45: 0 | J45: =I45*Appendix!$B$11 -> 0 | K45: =I45*Appendix!$B$9 -> 0 | L45: 0
B46: 28 | D46: 請求情報管理 | F46: 3.5 | G46: =F46*Appendix!$B$11 -> 1.05 | H46: =F46*Appendix!$B$9 -> 2.45 | I46: 0 | J46: =I46*Appendix!$B$11 -> 0 | K46: =I46*Appendix!$B$9 -> 0 | L46: 0
B47: 29 | D47: お知らせ登録 | F47: 3.5 | G47: =F47*Appendix!$B$11 -> 1.05 | H47: =F47*Appendix!$B$9 -> 2.45 | I47: 0 | J47: =I47*Appendix!$B$11 -> 0 | K47: =I47*Appendix!$B$9 -> 0 | L47: 0
B48: 30 | D48: マスタデータ登録 | F48: 3.5 | G48: =F48*Appendix!$B$11 -> 1.05 | H48: =F48*Appendix!$B$9 -> 2.45 | I48: 0 | J48: =I48*Appendix!$B$11 -> 0 | K48: =I48*Appendix!$B$9 -> 0 | L48: 0
B49: 31 | D49: システムメンテナンス | F49: 3.5 | G49: =F49*Appendix!$B$11 -> 1.05 | H49: =F49*Appendix!$B$9 -> 2.45 | I49: 0 | J49: =I49*Appendix!$B$11 -> 0 | K49: =I49*Appendix!$B$9 -> 0 | L49: 0
B50: 32 | D50: システムバックアップ | F50: 3.5 | G50: =F50*Appendix!$B$11 -> 1.05 | H50: =F50*Appendix!$B$9 -> 2.45 | I50: 0 | J50: =I50*Appendix!$B$11 -> 0 | K50: =I50*Appendix!$B$9 -> 0 | L50: 0
B51: 33 | D51: ログイン・ログアウト | F51: 1 | G51: =F51*Appendix!$B$11 -> 0.3 | H51: =F51*Appendix!$B$9 -> 0.7 | I51: 0 | J51: =I51*Appendix!$B$11 -> 0 | K51: =I51*Appendix!$B$9 -> 0 | L51: 0

Sheet 02_Native App
E1: ESTIMATION | L1: No: BM-2-901-22
L2: Version: 1.5
L3: Issue Date: 10/03/2026
B4: SUN ASTERISK VIETNAM CO., LTD | L4: ISO/IEC 27001:2022 & ISO 9001:2015
B6: Native(iOS/Android)
B8: Total (MM) | F8: =SUM(F13:F204)*(1+Appendix!$B$8)/Appendix!$B$13 -> 5.785 | G8: =SUM(G13:G204)*(1+Appendix!$B$8)/Appendix!$B$13 -> 1.7355 | H8: =SUM(H13:H204)*(1+Appendix!$B$8)/Appendix!$B$13 -> 4.0495 | I8: =SUM(I13:I204)*(1+Appendix!$B$8)/Appendix!$B$13 -> 5.85 | J8: =SUM(J13:J204)*(1+Appendix!$B$8)/Appendix!$B$13 -> 1.755 | K8: =SUM(K13:K204)*(1+Appendix!$B$8)/Appendix!$B$13 -> 4.095 | L8: =SUM(L13:L204)*(1+Appendix!$B$8)/Appendix!$B$13 -> 2.6
B10: No | C10: Category | D10: Screen・Feature | E10: Task | F10: Effort（Man-days） | M10: Note
F11: iOS | I11: Android | L11: DesignUX/UI
F12: Implement | G12: FixBug | H12: Unit Test | I12: Implement | J12: FixBug | K12: Unit Test
B13: 1 | C13: アカウント | D13: A0001 ログイン | F13: 2 | G13: =F13*Appendix!$B$11 -> 0.6 | H13: =F13*Appendix!$B$9 -> 1.4 | I13: 3 | J13: =I13*Appendix!$B$11 -> 0.9 | K13: =I13*Appendix!$B$9 -> 2.1 | L13: 1
B14: 2 | D14: A0005 アカウント新規登録 | F14: 4 | G14: =F14*Appendix!$B$11 -> 1.2 | H14: =F14*Appendix!$B$9 -> 2.8 | I14: 4 | J14: =I14*Appendix!$B$11 -> 1.2 | K14: =I14*Appendix!$B$9 -> 2.8 | L14: 2
B15: 3 | D15: A0002 PW再発行 | F15: 1 | G15: =F15*Appendix!$B$11 -> 0.3 | H15: =F15*Appendix!$B$9 -> 0.7 | I15: 1 | J15: =I15*Appendix!$B$11 -> 0.3 | K15: =I15*Appendix!$B$9 -> 0.7 | L15: 0
B16: 4 | D16: A0003 PW再設定 | F16: 1 | G16: =F16*Appendix!$B$11 -> 0.3 | H16: =F16*Appendix!$B$9 -> 0.7 | I16: 1 | J16: =I16*Appendix!$B$11 -> 0.3 | K16: =I16*Appendix!$B$9 -> 0.7 | L16: 0
B17: 5 | C17: 情報推移 | D17: A0011 各種情報推移 | F17: 14 | G17: =F17*Appendix!$B$11 -> 4.2 | H17: =F17*Appendix!$B$9 -> 9.8 | I17: 14 | J17: =I17*Appendix!$B$11 -> 4.2 | K17: =I17*Appendix!$B$9 -> 9.8 | L17: 0
B18: 6 | C18: メニュー | D18: A0009 メニュー検索 (popup) | F18: 2 | G18: =F18*Appendix!$B$11 -> 0.6 | H18: =F18*Appendix!$B$9 -> 1.4 | I18: 2 | J18: =I18*Appendix!$B$11 -> 0.6 | K18: =I18*Appendix!$B$9 -> 1.4 | L18: 5
B19: 7 | D19: A0009 メニュー登録・修正 | F19: 3 | G19: =F19*Appendix!$B$11 -> 0.9 | H19: =F19*Appendix!$B$9 -> 2.1 | I19: 3 | J19: =I19*Appendix!$B$11 -> 0.9 | K19: =I19*Appendix!$B$9 -> 2.1 | L19: 0
B20: 9 | C20: カレンダー | D20: A0012 アスリートカレンダー | F20: 9 | G20: =F20*Appendix!$B$11 -> 2.7 | H20: =F20*Appendix!$B$9 -> 6.3 | I20: 9 | J20: =I20*Appendix!$B$11 -> 2.7 | K20: =I20*Appendix!$B$9 -> 6.3 | L20: 0
B21: 10 | D21: A0007トレーニング状況登録 | F21: 4 | G21: =F21*Appendix!$B$11 -> 1.2 | H21: =F21*Appendix!$B$9 -> 2.8 | I21: 4 | J21: =I21*Appendix!$B$11 -> 1.2 | K21: =I21*Appendix!$B$9 -> 2.8 | L21: 0
B22: 11 | D22: A0010 栄養パランス | F22: 9 | G22: =F22*Appendix!$B$11 -> 2.7 | H22: =F22*Appendix!$B$9 -> 6.3 | I22: 9 | J22: =I22*Appendix!$B$11 -> 2.7 | K22: =I22*Appendix!$B$9 -> 6.3 | L22: 5
B23: 13 | D23: A0012 シーズン修正 (popup) | F23: 2 | G23: =F23*Appendix!$B$11 -> 0.6 | H23: =F23*Appendix!$B$9 -> 1.4 | I23: 2 | J23: =I23*Appendix!$B$11 -> 0.6 | K23: =I23*Appendix!$B$9 -> 1.4 | L23: 0
B24: 14 | C24: 目標 | D24: A0006 目標登録 | F24: 3 | G24: =F24*Appendix!$B$11 -> 0.9 | H24: =F24*Appendix!$B$9 -> 2.1 | I24: 3 | J24: =I24*Appendix!$B$11 -> 0.9 | K24: =I24*Appendix!$B$9 -> 2.1 | L24: 0
B25: 15 | C25: 身体状況 | D25: A0008 身体状況登録 | F25: 3 | G25: =F25*Appendix!$B$11 -> 0.9 | H25: =F25*Appendix!$B$9 -> 2.1 | I25: 3 | J25: =I25*Appendix!$B$11 -> 0.9 | K25: =I25*Appendix!$B$9 -> 2.1 | L25: 5
B26: 15 | D26: 体重計からBluetooth取り込む | F26: 5 | G26: =F26*Appendix!$B$11 -> 1.5 | H26: =F26*Appendix!$B$9 -> 3.5 | I26: 5 | J26: =I26*Appendix!$B$11 -> 1.5 | K26: =I26*Appendix!$B$9 -> 3.5 | L26: 5
B27: 16 | C27: メッセージ | D27: A0013 グループメッセージ | F27: 5 | G27: =F27*Appendix!$B$11 -> 1.5 | H27: =F27*Appendix!$B$9 -> 3.5 | I27: 5 | J27: =I27*Appendix!$B$11 -> 1.5 | K27: =I27*Appendix!$B$9 -> 3.5 | L27: 5
B28: 17 | D28: A0016 グループメッセージ詳細 | F28: 4 | G28: =F28*Appendix!$B$11 -> 1.2 | H28: =F28*Appendix!$B$9 -> 2.8 | I28: 4 | J28: =I28*Appendix!$B$11 -> 1.2 | K28: =I28*Appendix!$B$9 -> 2.8 | L28: 0
B29: 18 | C29: Myページ | D29: A0004 Myページ | F29: 5 | G29: =F29*Appendix!$B$11 -> 1.5 | H29: =F29*Appendix!$B$9 -> 3.5 | I29: 5 | J29: =I29*Appendix!$B$11 -> 1.5 | K29: =I29*Appendix!$B$9 -> 3.5 | L29: 0
B30: 19 | D30: 退会 Deactive | F30: 1 | G30: =F30*Appendix!$B$11 -> 0.3 | H30: =F30*Appendix!$B$9 -> 0.7 | I30: 1 | J30: =I30*Appendix!$B$11 -> 0.3 | K30: =I30*Appendix!$B$9 -> 0.7 | L30: 0
B31: 20 | D31: A0005 基本情報登録 | F31: 4 | G31: =F31*Appendix!$B$11 -> 1.2 | H31: =F31*Appendix!$B$9 -> 2.8 | I31: 4 | J31: =I31*Appendix!$B$11 -> 1.2 | K31: =I31*Appendix!$B$9 -> 2.8 | L31: 0
B32: 21 | D32: Create Material themes for App | F32: 4 | G32: =F32*Appendix!$B$11 -> 1.2 | H32: =F32*Appendix!$B$9 -> 2.8 | I32: 4 | J32: =I32*Appendix!$B$11 -> 1.2 | K32: =I32*Appendix!$B$9 -> 2.8 | L32: 6
B33: 22 | D33: Base Application + Setup API | F33: 4 | G33: =F33*Appendix!$B$11 -> 1.2 | H33: =F33*Appendix!$B$9 -> 2.8 | I33: 4 | J33: =I33*Appendix!$B$11 -> 1.2 | K33: =I33*Appendix!$B$9 -> 2.8 | L33: 6

Sheet 03_Infrastructure
E1: ESTIMATION | H1: No: BM-2-901-22
H2: Version: 1.5
H3: Issue Date: 10/03/2026
B4: SUN ASTERISK VIETNAM CO., LTD | H4: ISO/IEC 27001:2022 & ISO 9001:2015
B6: Infrastructure
B8: Total (MM) | F8: =SUM(F13:F188)*(1+Appendix!$B$8)/Appendix!$B$13 -> 0.78 | G8: =SUM(G13:G188)*(1+Appendix!$B$8)/Appendix!$B$13 -> 0.234
B10: No | C10: Category | D10: Feature | E10: Task | F10: Effort（Man-days） | H10: Note
F11: Infrastructure
F12: Implement | G12: FixBug
B13: 1 | C13: アカウント | D13: A0001 ログイン | F13: 2 | G13: =F13*Appendix!$B$11 -> 0.6
B14: 2 | D14: A0005 アカウント新規登録 | F14: 1 | G14: =F14*Appendix!$B$11 -> 0.3
B15: 3 | D15: A0002 PW再発行 | F15: 3 | G15: =F15*Appendix!$B$11 -> 0.9
B16: 4 | D16: A0003 PW再設定 | F16: 4 | G16: =F16*Appendix!$B$11 -> 1.2
B17: 5 | C17: 情報推移 | D17: A0011 各種情報推移 | F17: 2 | G17: =F17*Appendix!$B$11 -> 0.6

Sheet 04_Infrastructure for AWS
C1: ESTIMATION FOR AWS | I1: No: BM-2-901-22
I2: Version: 1.5
I3: Issue Date: 10/03/2026
A4: SUN ASTERISK VIETNAM CO., LTD | I4: ISO/IEC 27001:2022 & ISO 9001:2015
A5: * Dữ liệu trong bảng chỉ mang tính chất tham khảo. | E5: DEVELOPMENT | G5: STAGING | I5: PRODUCTION
B6: Total (MM) | E6: =Round(SUM(E10:E153)*(1+Appendix!$B$8)/Appendix!$B$13/Appendix!$B$14,1) -> 2.7 | F6: =Round(SUM(F10:F153)*(1+Appendix!$B$8)/Appendix!$B$13/Appendix!$B$14,1) -> 0.8 | G6: =Round(SUM(G10:G153)*(1+Appendix!$B$8)/Appendix!$B$13/Appendix!$B$14,1) -> 0.9 | H6: =Round(SUM(H10:H153)*(1+Appendix!$B$8)/Appendix!$B$13/Appendix!$B$14,1) -> 0.6 | I6: =Round(SUM(I10:I153)*(1+Appendix!$B$8)/Appendix!$B$13/Appendix!$B$14,1) -> 0.9 | J6: =Round(SUM(J10:J153)*(1+Appendix!$B$8)/Appendix!$B$13/Appendix!$B$14,1) -> 0.6 | K6: Note
A8: No | B8: Category | C8: Feature | E8: Effort（Man-hours） | G8: Effort（Man-hours） | I8: Effort（Man-hours）
E9: Implement | F9: Test/Fix | G9: Implement | H9: Test/Fix | I9: Implement | J9: Test/Fix
A10: 1 | B10: Designing Infra | C10: Infrastructure architecture | E10: 2 | F10: =ROUND(E10*0.3,0.5) -> 1 | G10: 0 | H10: 0 | I10: 0 | J10: 0 | K10: Design + est cost infra
C11: Estimate infrastructure cost and performance system | E11: 2 | F11: =ROUND(E11*0.3,0.5) -> 1 | G11: 0 | H11: 0 | I11: 0 | J11: 0
A12: 2 | B12: Config AWS account | C12: Create & Config AWS Account with AWS Organization | E12: 2 | F12: =ROUND(E12*0.3,0.5) -> 1 | G12: 0 | H12: 0 | I12: 0 | J12: 0 | K12: Centrally manage and govern your environment
A13: 3 | B13: Domain | C13: Create domain on AWS or Create hosted zones and add NS record to Japan site for management | E13: 2 | F13: =ROUND(E13*0.3,0.5) -> 1 | G13: 0 | H13: 0 | I13: 0 | J13: 0 | K13: Manage dns
A14: 4 | B14: Building AWS Environment | C14: Network | D14: - VPC | E14: 6 | F14: =E14*0.3 -> 1.8 | G14: =E14*0.3 -> 1.8 | H14: =F14*0.8 -> 1.44 | I14: =E14*0.3 -> 1.8 | J14: =F14*0.8 -> 1.44 | K14: Network for AWS
D15: - Config Subnets (Private & Public)
D16: - ACL for Private & Public
D17: - VPC Endpoint
D18: - Setting EIPs
D19: - NAT gateway, Internet Gateway & Add Routing
C20: Route 53 | D20: - Create ACM/SSL | E20: 2 | F20: =E20*0.3 -> 0.6 | G20: =E20*0.3 -> 0.6 | H20: =F20*0.8 -> 0.48 | I20: =E20*0.3 -> 0.6 | J20: =F20*0.8 -> 0.48 | K20: Manage customer's domain
D21: - Create records/sub domain
C22: IAM User | D22: - IAM-User | E22: 4 | F22: =E22*0.3 -> 1.2 | G22: =E22*0.3 -> 1.2 | H22: =F22*0.8 -> 0.96 | I22: =E22*0.3 -> 1.2 | J22: =F22*0.8 -> 0.96 | K22: Grant permission for user to access AWS console
D23: - IAM-Group (Readonly, Admin, Power, Development)
D24: - IAM-Policy for User & Group
C25: RDS Aurora | D25: - Create Security Group, Subnet group, Parameter group | E25: 3 | F25: =E25*0.3 -> 0.9 | G25: =E25*0.3 -> 0.9 | H25: =F25*0.8 -> 0.72 | I25: =E25*0.3 -> 0.9 | J25: =F25*0.8 -> 0.72 | K25: Database SQL
D26: - Create RDS Cluster
D27: - Create RDS Cluster Instance
D28: - Setting schedule backup database
C29: RDS | D29: - Create Security Group, Subnet group, Parameter group | E29: 3 | F29: =E29*0.3 -> 0.9 | G29: =E29*0.3 -> 0.9 | H29: =F29*0.8 -> 0.72 | I29: =E29*0.3 -> 0.9 | J29: =F29*0.8 -> 0.72 | K29: Database SQL
D30: - Create RDS Instance
D31: - Setting schedule backup database
C32: Dynamodb | D32: - Create table | E32: 3 | F32: =E32*0.3 -> 0.9 | G32: =E32*0.3 -> 0.9 | H32: =F32*0.8 -> 0.72 | I32: =E32*0.3 -> 0.9 | J32: =F32*0.8 -> 0.72 | K32: Database NoSQL
D33: - Create IAM role
C34: Elasticache | D34: - Create Security Group, Subnet group, Parameter group | E34: 3 | F34: =E34*0.3 -> 0.9 | G34: =E34*0.3 -> 0.9 | H34: =F34*0.8 -> 0.72 | I34: =E34*0.3 -> 0.9 | J34: =F34*0.8 -> 0.72 | K34: Redis
D35: - Create Cluster
D36: - Setting schedule backup redis
C37: Cognito | D37: - Create user pool | E37: 4 | F37: =E37*0.3 -> 1.2 | G37: =E37*0.3 -> 1.2 | H37: =F37*0.8 -> 0.96 | I37: =E37*0.3 -> 1.2 | J37: =F37*0.8 -> 0.96 | K37: Authentication - SSO
D38: - Sign in through external federated identity providers
C39: S3 for application | D39: - Create bucket and setting S3 policy | E39: 1 | F39: =E39*0.3 -> 0.3 | G39: =E39*0.3 -> 0.3 | H39: =F39*0.8 -> 0.24 | I39: =E39*0.3 -> 0.3 | J39: =F39*0.8 -> 0.24 | K39: Store static files of Application
D40: - S3 setting event
C41: S3 for log storage | D41: - Create bucket and setting S3 policy | E41: 1 | F41: =E41*0.3 -> 0.3 | G41: =E41*0.3 -> 0.3 | H41: =F41*0.8 -> 0.24 | I41: =E41*0.3 -> 0.3 | J41: =F41*0.8 -> 0.24 | K41: Store logs of ALB, CloudFront, and CloudTrail
D42: - S3 setting event
C43: SNS | D43: - Create topic | E43: 2 | F43: =E43*0.3 -> 0.6 | G43: =E43*0.3 -> 0.6 | H43: =F43*0.8 -> 0.48 | I43: =E43*0.3 -> 0.6 | J43: =F43*0.8 -> 0.48 | K43: Push notification
D44: - Setting policy, subscribe for alarm
C45: SSL | D45: - Request certificate in ACM | E45: 2 | F45: =E45*0.3 -> 0.6 | G45: =E45*0.3 -> 0.6 | H45: =F45*0.8 -> 0.48 | I45: =E45*0.3 -> 0.6 | J45: =F45*0.8 -> 0.48 | K45: Certificate for domain
C46: Cloudfront for ALB | D46: - Create distribution, create origin | E46: 4 | F46: =E46*0.3 -> 1.2 | G46: =E46*0.3 -> 1.2 | H46: =F46*0.8 -> 0.96 | I46: =E46*0.3 -> 1.2 | J46: =F46*0.8 -> 0.96 | K46: Setting content delivery network (CDN)
D47: - Create cache policy
D48: - Setting behavior
C49: Cloudfront for Frontend | D49: - Create distribution, create origin | E49: 4 | F49: =E49*0.3 -> 1.2 | G49: =E49*0.3 -> 1.2 | H49: =F49*0.8 -> 0.96 | I49: =E49*0.3 -> 1.2 | J49: =F49*0.8 -> 0.96 | K49: Setting content delivery network (CDN)
D50: - Create cache policy
D51: - Setting behavior
D52: - Create bucket and setting S3 policy
C53: Lambda for Application | D53: - Create function | E53: 4 | F53: =E53*0.3 -> 1.2 | G53: =E53*0.3 -> 1.2 | H53: =F53*0.8 -> 0.96 | I53: =E53*0.3 -> 1.2 | J53: =F53*0.8 -> 0.96 | K53: Handles certain business logic of the system
D54: - Create IAM role
D55: - Deploy function
C56: Lightsail Mysql | D56: - Create Database Mysql | E56: 4 | F56: =E56*0.3 -> 1.2 | G56: =E56*0.3 -> 1.2 | H56: =F56*0.8 -> 0.96 | I56: =E56*0.3 -> 1.2 | J56: =F56*0.8 -> 0.96 | K56: AWS Lightsail MySQL is a managed database service that simplifies setting up, managing, and scaling MySQL databases in the cloud
D57: - Setting Database
D58: - Schedule backup database
C59: Lightsail Instance | D59: - Create Instance | E59: 4 | F59: =E59*0.3 -> 1.2 | G59: =E59*0.3 -> 1.2 | H59: =F59*0.8 -> 0.96 | I59: =E59*0.3 -> 1.2 | J59: =F59*0.8 -> 0.96 | K59: AWS Lightsail Instance is a virtual server that provides simplified cloud hosting with predictable pricing.
D60: - Install and setting
D61: - Backup Insntace
C62: Lightsail Bucket | D62: - Create bucket | E62: 2 | F62: =E62*0.3 -> 0.6 | G62: =E62*0.3 -> 0.6 | H62: =F62*0.8 -> 0.48 | I62: =E62*0.3 -> 0.6 | J62: =F62*0.8 -> 0.48 | K62: AWS Lightsail Bucket provides scalable object storage for storing and managing data like images, videos, and backups.
C63: Lightsail Load Balancer | D63: - Create Load Balancer | E63: 2 | F63: =E63*0.3 -> 0.6 | G63: =E63*0.3 -> 0.6 | H63: =F63*0.8 -> 0.48 | I63: =E63*0.3 -> 0.6 | J63: =F63*0.8 -> 0.48 | K63: AWS Lightsail Load Balancer distributes traffic across instances for high availability and automatic scaling.
D64: - Setting route, ssl
C65: SES | D65: - Verify domain - verify email | E65: 2 | F65: =E65*0.3 -> 0.6 | G65: =E65*0.3 -> 0.6 | H65: =F65*0.8 -> 0.48 | I65: =E65*0.3 -> 0.6 | J65: =F65*0.8 -> 0.48 | K65: Send email
D66: - Move out sandbox (if need)
C67: SQS | D67: - Create queue | E67: 2 | F67: =E67*0.3 -> 0.6 | G67: =E67*0.3 -> 0.6 | H67: =F67*0.8 -> 0.48 | I67: =E67*0.3 -> 0.6 | J67: =F67*0.8 -> 0.48 | K67: Message Queue
D68: - Config queue
C69: Amplify | D69: - Create new app | E69: 8 | F69: =E69*0.3 -> 2.4 | G69: =E69*0.3 -> 2.4 | H69: =F69*0.8 -> 1.92 | I69: =E69*0.3 -> 2.4 | J69: =F69*0.8 -> 1.92 | K69: Host your simple marketing website or web application on AWS
D70: - Connect to repository
D71: - Confirm build configure
D72: - Deploy code to amplify
C73: Backup | D73: - Create Backup plan, Backup vault | E73: 4 | F73: =E73*0.3 -> 1.2 | G73: =E73*0.3 -> 1.2 | H73: =F73*0.8 -> 0.96 | I73: =E73*0.3 -> 1.2 | J73: =F73*0.8 -> 0.96 | K73: AWS Backup automates and manages the backup of data across AWS services, ensuring data protection and compliance
D74: - Associate with resources
C75: OpenSearch | D75: - Create domain | E75: 3 | F75: =E75*0.3 -> 0.9 | G75: =E75*0.3 -> 0.9 | H75: =F75*0.8 -> 0.72 | I75: =E75*0.3 -> 0.9 | J75: =F75*0.8 -> 0.72 | K75: Setup Search Engine
D76: - Config domain
C77: API Gateway | D77: - Create API Gateway | E77: 4 | F77: =E77*0.3 -> 1.2 | G77: =E77*0.3 -> 1.2 | H77: =F77*0.8 -> 0.96 | I77: =E77*0.3 -> 1.2 | J77: =F77*0.8 -> 0.96 | K77: API Gateway acts as a front door for applications, enabling secure and controlled access to backend services by managing and routing API requests
D78: - Create resource
D79: - Create method
D80: - Create stage
C81: GuardDuty | D81: - Enable | E81: 4 | F81: =E81*0.3 -> 1.2 | G81: =E81*0.3 -> 1.2 | H81: =F81*0.8 -> 0.96 | I81: =E81*0.3 -> 1.2 | J81: =F81*0.8 -> 0.96 | K81: Amazon GuardDuty is a threat detection service that continuously monitors your AWS accounts and workloads for malicious activity and unauthorized behavior
D82: - Setting data sources
D83: - Setting findings and notifications
C84: Config | D84: - Enable | E84: 3 | F84: =E84*0.3 -> 0.9 | G84: =E84*0.3 -> 0.9 | H84: =F84*0.8 -> 0.72 | I84: =E84*0.3 -> 0.9 | J84: =F84*0.8 -> 0.72 | K84: AWS Config enables you to assess, audit, and evaluate the configurations of your AWS resources to ensure compliance and secure management
D85: - Setting rules and notifications
C86: BedRock | D86: - Enable access model | E86: 4 | F86: =E86*0.3 -> 1.2 | G86: =E86*0.3 -> 1.2 | H86: =F86*0.8 -> 0.96 | I86: =E86*0.3 -> 1.2 | J86: =F86*0.8 -> 0.96 | K86: AWS Bedrock is a fully managed service that helps build and scale generative AI applications using pre-built models from leading AI providers
D87: - Setup permission
C88: WAF | D88: - Create Web ACL | E88: 3 | F88: =E88*0.3 -> 0.9 | G88: =E88*0.3 -> 0.9 | H88: =F88*0.8 -> 0.72 | I88: =E88*0.3 -> 0.9 | J88: =F88*0.8 -> 0.72 | K88: Web application firewall for CloudFront, ALB
D89: - Config rule
C90: QuickSight | D90: - Create QuickSight | E90: 8 | F90: =E90*0.3 -> 2.4 | G90: =E90*0.3 -> 2.4 | H90: =F90*0.8 -> 1.92 | I90: =E90*0.3 -> 2.4 | J90: =F90*0.8 -> 1.92 | K90: Amazon QuickSight is a fast, cloud-powered business intelligence service that makes it easy to create and publish interactive dashboards
D91: - Config and connect Data Source
D92: - Add user and permission
C93: Bastion Host | D93: - Create Security group | E93: 4 | F93: =E93*0.3 -> 1.2 | G93: =E93*0.3 -> 1.2 | H93: =F93*0.8 -> 0.96 | I93: =E93*0.3 -> 1.2 | J93: =F93*0.8 -> 0.96 | K93: Configured to withstand any network attacks
D94: - Create IAM role
D95: - Create Instance EC2
D96: - Setting server
C97: Container Registry (ECR) | D97: - Create and setting life cycle | E97: 1 | F97: =E97*0.3 -> 0.3 | G97: =E97*0.3 -> 0.3 | H97: =F97*0.8 -> 0.24 | I97: =E97*0.3 -> 0.3 | J97: =F97*0.8 -> 0.24 | K97: Create a repository (store images)
C98: Cluster ECS | D98: - Create cluster | E98: 1 | F98: =E98*0.3 -> 0.3 | G98: =E98*0.3 -> 0.3 | H98: =F98*0.8 -> 0.24 | I98: =E98*0.3 -> 0.3 | J98: =F98*0.8 -> 0.24 | K98: Cluster ECS
C99: Build & Deploy ECS Service Backend 1 | D99: - Setting ALB, Target Group for ALB (HTTP & HTTPS) | E99: 16 | F99: =E99*0.3 -> 4.8 | G99: =E99*0.3 -> 4.8 | H99: =F99*0.8 -> 3.84 | I99: =E99*0.3 -> 4.8 | J99: =F99*0.8 -> 3.84
D100: - Security Group for ALB
D101: - Create IAM role
...

Sheet 05_Resource plan
D1: ESTIMATION | S1: No: BM-2-901-22
S2: Version: 1.5
S3: Issue Date: 10/03/2026
A4: SUN ASTERISK VIETNAM CO., LTD | S4: ISO/IEC 27001:2013&ISO 9001:2015
B6: * Unit: Man-month
B7: Role | C7: Requirement Definition | F7: Basic Design | I7: Detail Design/Coding/Unit Test | Q7: Intergration Testing/System Test | U7: UAT | W7: Total
C8: 46023 | D8: 46054 | E8: 46082 | F8: 46113 | G8: 46143 | H8: 46174 | I8: 46204 | J8: 46235 | K8: 46266 | L8: 46296 | M8: 46327 | N8: 46357 | O8: 46388 | P8: 46419 | Q8: 46447 | R8: 46478 | S8: 46508 | T8: 46539 | U8: 46569 | V8: 46600
B9: 【SJP】Designer | W9: =sum(C9:V9) -> 0
B10: 【SVN】PL | W10: =sum(C10:V10) -> 0
B11: 【SVN】BrSE | W11: =sum(C11:V11) -> 0
B12: 【SVN】Backend Lead | W12: =sum(C12:V12) -> 0
B13: 【SVN】Backend | W13: =sum(C13:V13) -> 0
B14: 【SVN】Frontend Lead | W14: =sum(C14:V14) -> 0
B15: 【SVN】Frontend | W15: =sum(C15:V15) -> 0
B16: 【SVN】Native-app Lead | W16: =sum(C16:V16) -> 0
B17: 【SVN】Native-app | W17: =sum(C17:V17) -> 0
B18: 【SVN】QA Lead | W18: =sum(C18:V18) -> 0
B19: 【SVN】QA | W19: =sum(C19:V19) -> 0
B20: 【SVN】Infrastructure | W20: =sum(C20:V20) -> 0
... B22: 【SVN】Designer | W22: =sum(C22:V22) -> 0
B23: Total | C23: =SUM(C10:C22) -> 0 | D23: =SUM(D10:D22) -> 0 | E23: =SUM(E10:E22) -> 0 | F23: =SUM(F10:F22) -> 0 | G23: =SUM(G10:G22) -> 0 | H23: =SUM(H10:H22) -> 0 | I23: =SUM(I10:I22) -> 0 | J23: =SUM(J10:J22) -> 0 | ... W23: =SUM(W10:W22) -> 0
B24: Total phase | C24: =SUM(C23:E23) -> 0 | F24: =SUM(F23:H23) -> 0 | I24: =SUM(I23:P23) -> 0 | Q24: =SUM(Q23:T23) -> 0 | U24: =SUM(U23:V23) -> 0

Sheet Appendix
C1: ESTIMATION | E1: No: BM-2-901-22
E2: Version: 1.5
E3: Issue Date: 10/03/2026
A4: SUN ASTERISK VIETNAM CO., LTD | E4: ISO/IEC 27001:2022 & ISO 9001:2015
A7: Value | B7: Coefficient | C7: Note
A8: Buffer | B8: 0.3 | C8: 0.3
A9: Unit Test | B9: 0.7 | C9: Coefficient*Implement effort
A10: Unit Test (for AWS) | B10: 0.5 | C10: Coefficient*Implement effort
A11: Fixbug | B11: 0.3 | C11: Coefficient*Implement effort
A12: Management | B12: 0.2 | C12: Coefficient*Implement effort
A13: Working days in a month | B13: 20
A14: Working hours in a day | B14: 7
A15: * Have to estimate base on qualification of rank 3.5 developer
A16: * FrontEnd implement effort includes effort to integrate with backend and markup...etc...
A18: Development Strategy | B18: Type of service | C18: Web Rendering Method | E18: Admin template | F18: Server/Serverless | G18: IaC tool
A19: MVP / POC | B19: Web | C19: Server Side Redering (SSR) | E19: AdminLTE | F19: Server | G19: Terraform
A20: Full feature / MMP | B20: Mobile app | C20: Client Side Rendering (CSR) | E20: FilamentPHP | F20: Serverless | G20: CloudFormation
B21: PWA (Progressive Web App) | C21: Pre-Rendering: Server Side Rendering (Universal SSR) | E21: LaravelAdmin | G21: Bicep
C22: Pre-Rendering: Static Site Generation (SSG) | G22: Ansible
C23: Dynamic Rendering | G23: Chef
G24: Puppet
G25: CDK

Sheet Project Organization Structure 
L1: ESTIMATION | AJ1: No: BM-2-901-22
AJ2: Version: 1.5
AJ3: Issue Date: 10/03/2026
B4: SUN ASTERISK VIETNAM CO., LTD | AJ4: ISO/IEC 27001:2022 & ISO 9001:2015
